<mets:mets xmlns:mets="http://www.loc.gov/METS/" xmlns:xlink="http://www.w3.org/1999/xlink" xsi:schemaLocation="http://www.loc.gov/METS/ https://www.loc.gov/standards/mets/mets.xsd" OBJID="oai:wwu.de:80a6f07f-0ee0-4b6a-96aa-49586bff16bb" LABEL="University of Muenster, Institutional Repository MIAMI"  xmlns:xsi="http://www.w3.org/2001/XMLSchema-instance">
          <mets:metsHdr CREATEDATE="2022-04-07T09:39:27">
            <mets:agent TYPE="OTHER" ROLE="OTHER" OTHERTYPE="SOFTWARE">
              <mets:name>Memory Alpha</mets:name>
            </mets:agent>
          </mets:metsHdr>
          <mets:dmdSec ID="DMD_80a6f07f-0ee0-4b6a-96aa-49586bff16bb">
            <mets:mdWrap MIMETYPE="text/xml" MDTYPE="MODS">
              <mets:xmlData>
                <mods:mods xmlns:mods="http://www.loc.gov/mods/v3" xsi:schemaLocation="http://www.loc.gov/mods/v3 http://www.loc.gov/standards/mods/v3/mods-3-7.xsd" version="3.7">
                  <mods:titleInfo type="uniform" lang="eng">
                    <mods:title script="Latn">Exploring market knowledge in product development of chemical firms</mods:title>
                  </mods:titleInfo>
                  <mods:name type="personal" valueURI="http://d-nb.info/gnd/1140584405">
                    <mods:namePart type="given">Armand</mods:namePart>
                    <mods:namePart type="family">Smits</mods:namePart>
                    <mods:displayForm>Smits, Armand</mods:displayForm>
                    <mods:affiliation>FB 12: Chemie und Pharmazie</mods:affiliation>
                    <mods:role>
                      <mods:roleTerm type="code" authority="marcrelator">aut</mods:roleTerm>
                    </mods:role>
                  </mods:name>
                  <mods:name type="personal" valueURI="http://d-nb.info/gnd/1055653899">
                    <mods:namePart type="given">Geert</mods:namePart>
                    <mods:namePart type="family">Vissers</mods:namePart>
                    <mods:displayForm>Vissers, Geert</mods:displayForm>
                    <mods:affiliation>FB 12: Chemie und Pharmazie</mods:affiliation>
                    <mods:role>
                      <mods:roleTerm type="code" authority="marcrelator">aut</mods:roleTerm>
                    </mods:role>
                  </mods:name>
                  <mods:name type="personal" valueURI="http://d-nb.info/gnd/170318605">
                    <mods:namePart type="given">Bernard</mods:namePart>
                    <mods:namePart type="family">Dankbaar</mods:namePart>
                    <mods:namePart type="date">1948-</mods:namePart>
                    <mods:displayForm>Dankbaar, Bernard</mods:displayForm>
                    <mods:affiliation>FB 12: Chemie und Pharmazie</mods:affiliation>
                    <mods:role>
                      <mods:roleTerm type="code" authority="marcrelator">aut</mods:roleTerm>
                    </mods:role>
                  </mods:name>
                  <mods:name type="corporate" valueURI="http://d-nb.info/gnd/5091030-9" altRepGroup="3">
                    <mods:namePart>Universitäts- und Landesbibliothek Münster</mods:namePart>
                    <mods:role>
                      <mods:roleTerm type="code" authority="marcrelator">own</mods:roleTerm>
                    </mods:role>
                  </mods:name>
                  <mods:name type="corporate" valueURI="http://d-nb.info/gnd/5091030-9" altRepGroup="3">
                    <mods:namePart>Münster, Westfalen / ULB</mods:namePart>
                    <mods:role>
                      <mods:roleTerm type="code" authority="marcrelator">own</mods:roleTerm>
                    </mods:role>
                  </mods:name>
                  <mods:name type="corporate" valueURI="http://d-nb.info/gnd/5091030-9" altRepGroup="3">
                    <mods:namePart>Münster, Westfalen / Landesbibliothek</mods:namePart>
                    <mods:role>
                      <mods:roleTerm type="code" authority="marcrelator">own</mods:roleTerm>
                    </mods:role>
                  </mods:name>
                  <mods:name type="corporate" valueURI="http://d-nb.info/gnd/5091030-9" altRepGroup="3">
                    <mods:namePart>Westfalen / Universität Münster / Universitäts- und Landesbibliothek</mods:namePart>
                    <mods:role>
                      <mods:roleTerm type="code" authority="marcrelator">own</mods:roleTerm>
                    </mods:role>
                  </mods:name>
                  <mods:genre>article</mods:genre>
                  <mods:genre authority="dct">Text</mods:genre>
                  <mods:originInfo>
                    <mods:dateIssued keyDate="yes">2011</mods:dateIssued>
                    <mods:dateOther keyDate="yes" encoding="w3cdtf">2011-03-10</mods:dateOther>
                  </mods:originInfo>
                  <mods:originInfo>
                    <mods:dateIssued encoding="w3cdtf">2011-03-09</mods:dateIssued>
                    <mods:dateModified encoding="w3cdtf">2016-03-18</mods:dateModified>
                    <mods:edition>[Electronic ed.]</mods:edition>
                  </mods:originInfo>
                  <mods:language>
                    <mods:languageTerm type="code" authority="iso639-2b">eng</mods:languageTerm>
                  </mods:language>
                  <mods:physicalDescription>
                    <mods:form>electronic</mods:form>
                    <mods:reformattingQuality>access</mods:reformattingQuality>
                    <mods:internetMediaType>application/pdf</mods:internetMediaType>
                    <mods:extent>17-33</mods:extent>
                    <mods:digitalOrigin>born digital</mods:digitalOrigin>
                  </mods:physicalDescription>
                  <mods:abstract lang="eng">Firms can enhance product innovation performance by continuously staying in touch with customers and the market in general. While studies on market oriented product development have identified several general dimensions of market knowledge used in product innovation, the nature of market knowledge that is specifically important in the chemical industry remains unclear. Because firm relevant knowledge resources are increasingly seen as being industry specific, filling this gap becomes more relevant. This study uses a multiple case study of six product innovation projects in six different companies to identify important market knowledge dimensions in the product development of chemical firms. Aggregated results from the six cases point to segment knowledge, application knowledge, product usage knowledge, and customer knowledge as being important market knowledge dimensions. Implications for theory and practice as well as avenues for further research are included.&lt;br&gt;</mods:abstract>
                  <mods:note type="content">Section "Research Paper"</mods:note>
                  <mods:classification authority="ddc">330</mods:classification>
                  <mods:relatedItem type="host">
                    <mods:titleInfo>
                      <mods:title script="Latn">Journal of Business Chemistry</mods:title>
                    </mods:titleInfo>
                    <mods:part type="issue" order="1">
                      <mods:detail>
                        <mods:number>8 (2011) 1</mods:number>
                      </mods:detail>
                      <mods:extent unit="pages">
                        <mods:start>17</mods:start>
                        <mods:end>33</mods:end>
                      </mods:extent>
                    </mods:part>
                    <mods:recordInfo>
                      <mods:recordIdentifier>oai:wwu.de:30ea0d44-f69a-4d4b-947c-e84260d58208</mods:recordIdentifier>
                    </mods:recordInfo>
                  </mods:relatedItem>
                  <mods:identifier type="urn">urn:nbn:de:hbz:6-34499413636</mods:identifier>
                  <mods:location>
                    <mods:url access="object in context">https://miami.uni-muenster.de/Record/80a6f07f-0ee0-4b6a-96aa-49586bff16bb</mods:url>
                  </mods:location>
                  <mods:accessCondition type="use and reproduction">
                    <mods:extension>
                      <ma:maWrap xmlns:ma="http://memoryalpha.ulb.uni-muenster.de">
                        <ma:licence>
                          <ma:displayLabel>InC 1.0</ma:displayLabel>
                          <ma:targetUrl>https://rightsstatements.org/vocab/InC/1.0/</ma:targetUrl>
                        </ma:licence>
                      </ma:maWrap>
                    </mods:extension>
                  </mods:accessCondition>
                  <mods:recordInfo>
                    <mods:recordIdentifier>oai:wwu.de:80a6f07f-0ee0-4b6a-96aa-49586bff16bb</mods:recordIdentifier>
                  </mods:recordInfo>
                </mods:mods>
              </mets:xmlData>
            </mets:mdWrap>
          </mets:dmdSec>
          <mets:amdSec ID="AMD_80a6f07f-0ee0-4b6a-96aa-49586bff16bb">
            <mets:rightsMD ID="RIGHTSMD_80a6f07f-0ee0-4b6a-96aa-49586bff16bb">
              <mets:mdWrap MDTYPE="OTHER" MIMETYPE="text/xml" OTHERMDTYPE="DVRIGHTS">
                <mets:xmlData>
                  <dv:rights xmlns:dv="http://dfg-viewer.de/">
                    <dv:owner>Universitäts- und Landesbibliothek Münster</dv:owner>
                  </dv:rights>
                </mets:xmlData>
              </mets:mdWrap>
            </mets:rightsMD>
            <mets:digiprovMD ID="DIGIPROVMD_80a6f07f-0ee0-4b6a-96aa-49586bff16bb">
              <mets:mdWrap MDTYPE="OTHER" MIMETYPE="text/xml" OTHERMDTYPE="DVLINKS">
                <mets:xmlData>
                  <dv:links xmlns:dv="http://dfg-viewer.de/">
                    <dv:reference>https://miami.uni-muenster.de/Record/80a6f07f-0ee0-4b6a-96aa-49586bff16bb</dv:reference>
                    <dv:presentation/>
                  </dv:links>
                </mets:xmlData>
              </mets:mdWrap>
            </mets:digiprovMD>
          </mets:amdSec>
          <mets:fileSec>
            <mets:fileGrp USE="DEFAULT">
              <mets:file MIMETYPE="application/pdf" CHECKSUM="6bf90e61c2291f706bc4b5b7815a4964fe7de7acd3d13da0d66f7335a28d7fab" CREATED="2016-03-18T10:50:45" CHECKSUMTYPE="SHA-256" SIZE="360642" ID="ID_FIL_2011_vol8_iss1_17-33.pdf_DEFAULT">
                <mets:FLocat xlink:href="https://repositorium.uni-muenster.de/document/miami/80a6f07f-0ee0-4b6a-96aa-49586bff16bb/2011_vol8_iss1_17-33.pdf" LOCTYPE="URL"/>
              </mets:file>
            </mets:fileGrp>
            <mets:fileGrp USE="DOWNLOAD">
              <mets:file MIMETYPE="application/pdf" ID="DOW80a6f07f-0ee0-4b6a-96aa-49586bff16bb">
                <mets:FLocat xlink:href="https://repositorium.uni-muenster.de/transfer/miami/80a6f07f-0ee0-4b6a-96aa-49586bff16bb" LOCTYPE="URL"/>
              </mets:file>
            </mets:fileGrp>
          </mets:fileSec>
          <mets:structMap TYPE="PHYSICAL">
            <mets:div ID="ID_PHY_80a6f07f-0ee0-4b6a-96aa-49586bff16bb" TYPE="physSequence">
              <mets:div ID="ID_PHY_2011_vol8_iss1_17-33.pdf">
                <mets:fptr FILEID="ID_FIL_2011_vol8_iss1_17-33.pdf_DEFAULT"/>
              </mets:div>
            </mets:div>
          </mets:structMap>
          <mets:structMap TYPE="LOGICAL">
            <mets:div ADMID="AMD_80a6f07f-0ee0-4b6a-96aa-49586bff16bb" DMDID="DMD_80a6f07f-0ee0-4b6a-96aa-49586bff16bb" ID="ID_LOG_80a6f07f-0ee0-4b6a-96aa-49586bff16bb" TYPE="Monograph">
              <mets:div ID="ID_LOG_ID_PHY_2011_vol8_iss1_17-33.pdf"/>
            </mets:div>
          </mets:structMap>
          <mets:structLink>
            <mets:smLink xlink:from="ID_LOG_80a6f07f-0ee0-4b6a-96aa-49586bff16bb" xlink:to="ID_PHY_80a6f07f-0ee0-4b6a-96aa-49586bff16bb"/>
            <mets:smLink xlink:from="ID_LOG_ID_PHY_2011_vol8_iss1_17-33.pdf" xlink:to="ID_PHY_2011_vol8_iss1_17-33.pdf"/>
          </mets:structLink>
        </mets:mets>