<mets:mets xmlns:mets="http://www.loc.gov/METS/" xmlns:xlink="http://www.w3.org/1999/xlink" xsi:schemaLocation="http://www.loc.gov/METS/ https://www.loc.gov/standards/mets/mets.xsd" OBJID="oai:wwu.de:b8e759e0-8795-4cb6-b087-e829b26982cc" LABEL="University of Muenster, Institutional Repository MIAMI"  xmlns:xsi="http://www.w3.org/2001/XMLSchema-instance">
          <mets:metsHdr CREATEDATE="2022-04-07T09:34:47">
            <mets:agent TYPE="OTHER" ROLE="OTHER" OTHERTYPE="SOFTWARE">
              <mets:name>Memory Alpha</mets:name>
            </mets:agent>
          </mets:metsHdr>
          <mets:dmdSec ID="DMD_b8e759e0-8795-4cb6-b087-e829b26982cc">
            <mets:mdWrap MIMETYPE="text/xml" MDTYPE="MODS">
              <mets:xmlData>
                <mods:mods xmlns:mods="http://www.loc.gov/mods/v3" xsi:schemaLocation="http://www.loc.gov/mods/v3 http://www.loc.gov/standards/mods/v3/mods-3-7.xsd" version="3.7">
                  <mods:titleInfo type="uniform" lang="ger">
                    <mods:title script="Latn">Artikel 1 GRCh - Die Menschenwürde im Unionsrecht</mods:title>
                  </mods:titleInfo>
                  <mods:name type="personal" valueURI="http://d-nb.info/gnd/1023232987">
                    <mods:namePart type="given">Astrid</mods:namePart>
                    <mods:namePart type="family">Berlth</mods:namePart>
                    <mods:displayForm>Berlth, Astrid</mods:displayForm>
                    <mods:affiliation>FB 03: Rechtswissenschaftliche Fakultät</mods:affiliation>
                    <mods:role>
                      <mods:roleTerm type="code" authority="marcrelator">aut</mods:roleTerm>
                    </mods:role>
                  </mods:name>
                  <mods:name type="personal" valueURI="http://d-nb.info/gnd/110735196" altRepGroup="1">
                    <mods:namePart type="given">Hans-Michael</mods:namePart>
                    <mods:namePart type="family">Wolffgang</mods:namePart>
                    <mods:namePart type="date">1953-</mods:namePart>
                    <mods:displayForm>Wolffgang, Hans-Michael</mods:displayForm>
                    <mods:affiliation>FB 03: Rechtswissenschaftliche Fakultät</mods:affiliation>
                    <mods:role>
                      <mods:roleTerm type="code" authority="marcrelator">ths</mods:roleTerm>
                    </mods:role>
                  </mods:name>
                  <mods:name type="personal" valueURI="http://d-nb.info/gnd/110735196" altRepGroup="1">
                    <mods:namePart type="given">Hans Michael</mods:namePart>
                    <mods:namePart type="family">Wolffgang</mods:namePart>
                    <mods:namePart type="date">1953-</mods:namePart>
                    <mods:displayForm>Wolffgang, Hans Michael</mods:displayForm>
                    <mods:affiliation>FB 03: Rechtswissenschaftliche Fakultät</mods:affiliation>
                    <mods:role>
                      <mods:roleTerm type="code" authority="marcrelator">ths</mods:roleTerm>
                    </mods:role>
                  </mods:name>
                  <mods:name type="personal" valueURI="http://d-nb.info/gnd/110735196" altRepGroup="1">
                    <mods:namePart type="given">Hans-M.</mods:namePart>
                    <mods:namePart type="family">Wolffgang</mods:namePart>
                    <mods:namePart type="date">1953-</mods:namePart>
                    <mods:displayForm>Wolffgang, Hans-M.</mods:displayForm>
                    <mods:affiliation>FB 03: Rechtswissenschaftliche Fakultät</mods:affiliation>
                    <mods:role>
                      <mods:roleTerm type="code" authority="marcrelator">ths</mods:roleTerm>
                    </mods:role>
                  </mods:name>
                  <mods:name type="personal" valueURI="http://d-nb.info/gnd/110735196" altRepGroup="1">
                    <mods:namePart type="given">Hans M.</mods:namePart>
                    <mods:namePart type="family">Wolffgang</mods:namePart>
                    <mods:namePart type="date">1953-</mods:namePart>
                    <mods:displayForm>Wolffgang, Hans M.</mods:displayForm>
                    <mods:affiliation>FB 03: Rechtswissenschaftliche Fakultät</mods:affiliation>
                    <mods:role>
                      <mods:roleTerm type="code" authority="marcrelator">ths</mods:roleTerm>
                    </mods:role>
                  </mods:name>
                  <mods:name type="personal" valueURI="http://d-nb.info/gnd/110735196" altRepGroup="1">
                    <mods:namePart type="given">H.-M.</mods:namePart>
                    <mods:namePart type="family">Wolffgang</mods:namePart>
                    <mods:namePart type="date">1953-</mods:namePart>
                    <mods:displayForm>Wolffgang, H.-M.</mods:displayForm>
                    <mods:affiliation>FB 03: Rechtswissenschaftliche Fakultät</mods:affiliation>
                    <mods:role>
                      <mods:roleTerm type="code" authority="marcrelator">ths</mods:roleTerm>
                    </mods:role>
                  </mods:name>
                  <mods:name type="personal" valueURI="http://d-nb.info/gnd/110735196" altRepGroup="1">
                    <mods:namePart type="given">H. M.</mods:namePart>
                    <mods:namePart type="family">Wolffgang</mods:namePart>
                    <mods:namePart type="date">1953-</mods:namePart>
                    <mods:displayForm>Wolffgang, H. M.</mods:displayForm>
                    <mods:affiliation>FB 03: Rechtswissenschaftliche Fakultät</mods:affiliation>
                    <mods:role>
                      <mods:roleTerm type="code" authority="marcrelator">ths</mods:roleTerm>
                    </mods:role>
                  </mods:name>
                  <mods:name type="corporate" valueURI="http://d-nb.info/gnd/5091030-9" altRepGroup="2">
                    <mods:namePart>Universitäts- und Landesbibliothek Münster</mods:namePart>
                    <mods:role>
                      <mods:roleTerm type="code" authority="marcrelator">own</mods:roleTerm>
                    </mods:role>
                  </mods:name>
                  <mods:name type="corporate" valueURI="http://d-nb.info/gnd/5091030-9" altRepGroup="2">
                    <mods:namePart>Münster, Westfalen / ULB</mods:namePart>
                    <mods:role>
                      <mods:roleTerm type="code" authority="marcrelator">own</mods:roleTerm>
                    </mods:role>
                  </mods:name>
                  <mods:name type="corporate" valueURI="http://d-nb.info/gnd/5091030-9" altRepGroup="2">
                    <mods:namePart>Münster, Westfalen / Landesbibliothek</mods:namePart>
                    <mods:role>
                      <mods:roleTerm type="code" authority="marcrelator">own</mods:roleTerm>
                    </mods:role>
                  </mods:name>
                  <mods:name type="corporate" valueURI="http://d-nb.info/gnd/5091030-9" altRepGroup="2">
                    <mods:namePart>Westfalen / Universität Münster / Universitäts- und Landesbibliothek</mods:namePart>
                    <mods:role>
                      <mods:roleTerm type="code" authority="marcrelator">own</mods:roleTerm>
                    </mods:role>
                  </mods:name>
                  <mods:genre>doctoralThesis</mods:genre>
                  <mods:genre authority="dct">Text</mods:genre>
                  <mods:originInfo>
                    <mods:dateIssued keyDate="yes">2012</mods:dateIssued>
                    <mods:dateOther encoding="w3cdtf">2011-11-22</mods:dateOther>
                  </mods:originInfo>
                  <mods:originInfo>
                    <mods:dateIssued encoding="w3cdtf">2012-06-10</mods:dateIssued>
                    <mods:dateModified encoding="w3cdtf">2016-06-07</mods:dateModified>
                    <mods:edition>[Electronic ed.]</mods:edition>
                  </mods:originInfo>
                  <mods:language>
                    <mods:languageTerm type="code" authority="iso639-2b">ger</mods:languageTerm>
                  </mods:language>
                  <mods:physicalDescription>
                    <mods:internetMediaType>application/pdf</mods:internetMediaType>
                  </mods:physicalDescription>
                  <mods:abstract lang="ger">Durch die Kodifizierung der Menschenwürde an der Spitze der Charta der Grundrechte der Europäischen Union hat der Grundrechtekonvent ein von der Rechtsprechung des Europäischen Gerichthofes bis dahin nur touchiertes Grundrecht sichtbar gemacht. &#13;
In der vorliegenden Arbeit werden die Hintergründe der Menschenwürdegarantie in der Europäischen Union beleuchtet und ihr Stand in deren Grundrechtsarchitektur untersucht. Dabei werden insbesondere die Doppelnatur von Artikel 1 GRCh als Grundrecht mit subjektiv-rechtlicher Dimension und als objektiv-rechtlicher Grundsatz sowie seine Bedeutung für den ersten Titel der GRCh beleuchtet. Erkenntnisse liefern hierzu unter anderem die Verfassungen der Mitgliedstaaten der Europäischen Union, sowie die Rechtsprechung des Luxemburger Gerichtshofes.</mods:abstract>
                  <mods:subject>
                    <mods:topic lang="ger">Menschenwürde; Grundrechtecharta; Unionsgrundrechte; Biopatentrichtlinie; Omega-Spielhallen; Wesensgehalt</mods:topic>
                  </mods:subject>
                  <mods:classification authority="ddc">340</mods:classification>
                  <mods:identifier type="urn">urn:nbn:de:hbz:6-30439446686</mods:identifier>
                  <mods:location>
                    <mods:url access="object in context">https://miami.uni-muenster.de/Record/b8e759e0-8795-4cb6-b087-e829b26982cc</mods:url>
                  </mods:location>
                  <mods:accessCondition type="use and reproduction">
                    <mods:extension>
                      <ma:maWrap xmlns:ma="http://memoryalpha.ulb.uni-muenster.de">
                        <ma:licence>
                          <ma:displayLabel>InC 1.0</ma:displayLabel>
                          <ma:targetUrl>https://rightsstatements.org/vocab/InC/1.0/</ma:targetUrl>
                        </ma:licence>
                      </ma:maWrap>
                    </mods:extension>
                  </mods:accessCondition>
                  <mods:recordInfo>
                    <mods:recordIdentifier>oai:wwu.de:b8e759e0-8795-4cb6-b087-e829b26982cc</mods:recordIdentifier>
                  </mods:recordInfo>
                </mods:mods>
              </mets:xmlData>
            </mets:mdWrap>
          </mets:dmdSec>
          <mets:amdSec ID="AMD_b8e759e0-8795-4cb6-b087-e829b26982cc">
            <mets:rightsMD ID="RIGHTSMD_b8e759e0-8795-4cb6-b087-e829b26982cc">
              <mets:mdWrap MDTYPE="OTHER" MIMETYPE="text/xml" OTHERMDTYPE="DVRIGHTS">
                <mets:xmlData>
                  <dv:rights xmlns:dv="http://dfg-viewer.de/">
                    <dv:owner>Universitäts- und Landesbibliothek Münster</dv:owner>
                  </dv:rights>
                </mets:xmlData>
              </mets:mdWrap>
            </mets:rightsMD>
            <mets:digiprovMD ID="DIGIPROVMD_b8e759e0-8795-4cb6-b087-e829b26982cc">
              <mets:mdWrap MDTYPE="OTHER" MIMETYPE="text/xml" OTHERMDTYPE="DVLINKS">
                <mets:xmlData>
                  <dv:links xmlns:dv="http://dfg-viewer.de/">
                    <dv:reference>https://miami.uni-muenster.de/Record/b8e759e0-8795-4cb6-b087-e829b26982cc</dv:reference>
                    <dv:presentation/>
                  </dv:links>
                </mets:xmlData>
              </mets:mdWrap>
            </mets:digiprovMD>
          </mets:amdSec>
          <mets:fileSec>
            <mets:fileGrp USE="DEFAULT">
              <mets:file MIMETYPE="application/pdf" CHECKSUM="9dfa27b37935b22899afb966fb5e36a6919ddcca270f570735d0f4c30c7dd4b2" CREATED="2016-06-07T13:41:30" CHECKSUMTYPE="SHA-256" SIZE="1612484" ID="ID_FIL_diss_berlth.pdf_DEFAULT">
                <mets:FLocat xlink:href="https://repositorium.uni-muenster.de/document/miami/b8e759e0-8795-4cb6-b087-e829b26982cc/diss_berlth.pdf" LOCTYPE="URL"/>
              </mets:file>
            </mets:fileGrp>
            <mets:fileGrp USE="DOWNLOAD">
              <mets:file MIMETYPE="application/pdf" ID="DOWb8e759e0-8795-4cb6-b087-e829b26982cc">
                <mets:FLocat xlink:href="https://repositorium.uni-muenster.de/transfer/miami/b8e759e0-8795-4cb6-b087-e829b26982cc" LOCTYPE="URL"/>
              </mets:file>
            </mets:fileGrp>
          </mets:fileSec>
          <mets:structMap TYPE="PHYSICAL">
            <mets:div ID="ID_PHY_b8e759e0-8795-4cb6-b087-e829b26982cc" TYPE="physSequence">
              <mets:div ID="ID_PHY_diss_berlth.pdf">
                <mets:fptr FILEID="ID_FIL_diss_berlth.pdf_DEFAULT"/>
              </mets:div>
            </mets:div>
          </mets:structMap>
          <mets:structMap TYPE="LOGICAL">
            <mets:div ADMID="AMD_b8e759e0-8795-4cb6-b087-e829b26982cc" DMDID="DMD_b8e759e0-8795-4cb6-b087-e829b26982cc" ID="ID_LOG_b8e759e0-8795-4cb6-b087-e829b26982cc" TYPE="Monograph">
              <mets:div ID="ID_LOG_ID_PHY_diss_berlth.pdf"/>
            </mets:div>
          </mets:structMap>
          <mets:structLink>
            <mets:smLink xlink:from="ID_LOG_b8e759e0-8795-4cb6-b087-e829b26982cc" xlink:to="ID_PHY_b8e759e0-8795-4cb6-b087-e829b26982cc"/>
            <mets:smLink xlink:from="ID_LOG_ID_PHY_diss_berlth.pdf" xlink:to="ID_PHY_diss_berlth.pdf"/>
          </mets:structLink>
        </mets:mets>