<mets:mets xmlns:mets="http://www.loc.gov/METS/" xmlns:xlink="http://www.w3.org/1999/xlink" xsi:schemaLocation="http://www.loc.gov/METS/ https://www.loc.gov/standards/mets/mets.xsd" OBJID="oai:wwu.de:d031be29-f6f4-45c7-9a04-f68a22fdb467" LABEL="University of Muenster, Institutional Repository MIAMI"  xmlns:xsi="http://www.w3.org/2001/XMLSchema-instance">
          <mets:metsHdr CREATEDATE="2022-04-07T09:36:52">
            <mets:agent TYPE="OTHER" ROLE="OTHER" OTHERTYPE="SOFTWARE">
              <mets:name>Memory Alpha</mets:name>
            </mets:agent>
          </mets:metsHdr>
          <mets:dmdSec ID="DMD_d031be29-f6f4-45c7-9a04-f68a22fdb467">
            <mets:mdWrap MIMETYPE="text/xml" MDTYPE="MODS">
              <mets:xmlData>
                <mods:mods xmlns:mods="http://www.loc.gov/mods/v3" xsi:schemaLocation="http://www.loc.gov/mods/v3 http://www.loc.gov/standards/mods/v3/mods-3-7.xsd" version="3.7">
                  <mods:titleInfo type="uniform" lang="ger">
                    <mods:title script="Latn">Der Zentralteil des grönländischen Inlandeises</mods:title>
                    <mods:subTitle>Ergebnisse aus hochauflösenden elektromagnetischen Reflexionsmessungen</mods:subTitle>
                  </mods:titleInfo>
                  <mods:name type="personal" valueURI="http://d-nb.info/gnd/133581977">
                    <mods:namePart type="given">Ludwig</mods:namePart>
                    <mods:namePart type="family">Hempel</mods:namePart>
                    <mods:namePart type="date">1963-</mods:namePart>
                    <mods:displayForm>Hempel, Ludwig</mods:displayForm>
                    <mods:affiliation>FB 11: Physik</mods:affiliation>
                    <mods:role>
                      <mods:roleTerm type="code" authority="marcrelator">aut</mods:roleTerm>
                    </mods:role>
                  </mods:name>
                  <mods:name type="personal" valueURI="http://d-nb.info/gnd/125547277">
                    <mods:namePart type="given">Franz Johannes</mods:namePart>
                    <mods:namePart type="family">Thyssen</mods:namePart>
                    <mods:displayForm>Thyssen, Franz Johannes</mods:displayForm>
                    <mods:affiliation>FB 11: Physik</mods:affiliation>
                    <mods:role>
                      <mods:roleTerm type="code" authority="marcrelator">ths</mods:roleTerm>
                    </mods:role>
                  </mods:name>
                  <mods:name type="corporate" valueURI="http://d-nb.info/gnd/5091030-9" altRepGroup="2">
                    <mods:namePart>Universitäts- und Landesbibliothek Münster</mods:namePart>
                    <mods:role>
                      <mods:roleTerm type="code" authority="marcrelator">own</mods:roleTerm>
                    </mods:role>
                  </mods:name>
                  <mods:name type="corporate" valueURI="http://d-nb.info/gnd/5091030-9" altRepGroup="2">
                    <mods:namePart>Münster, Westfalen / ULB</mods:namePart>
                    <mods:role>
                      <mods:roleTerm type="code" authority="marcrelator">own</mods:roleTerm>
                    </mods:role>
                  </mods:name>
                  <mods:name type="corporate" valueURI="http://d-nb.info/gnd/5091030-9" altRepGroup="2">
                    <mods:namePart>Münster, Westfalen / Landesbibliothek</mods:namePart>
                    <mods:role>
                      <mods:roleTerm type="code" authority="marcrelator">own</mods:roleTerm>
                    </mods:role>
                  </mods:name>
                  <mods:name type="corporate" valueURI="http://d-nb.info/gnd/5091030-9" altRepGroup="2">
                    <mods:namePart>Westfalen / Universität Münster / Universitäts- und Landesbibliothek</mods:namePart>
                    <mods:role>
                      <mods:roleTerm type="code" authority="marcrelator">own</mods:roleTerm>
                    </mods:role>
                  </mods:name>
                  <mods:genre>book</mods:genre>
                  <mods:genre authority="dct">Text</mods:genre>
                  <mods:originInfo>
                    <mods:dateCaptured keyDate="yes">1994</mods:dateCaptured>
                    <mods:dateOther encoding="w3cdtf">1994-11-17</mods:dateOther>
                  </mods:originInfo>
                  <mods:originInfo>
                    <mods:dateIssued encoding="w3cdtf">2005-10-26</mods:dateIssued>
                    <mods:dateModified encoding="w3cdtf">2016-06-14</mods:dateModified>
                    <mods:edition>[Electronic ed.]</mods:edition>
                  </mods:originInfo>
                  <mods:language>
                    <mods:languageTerm type="code" authority="iso639-2b">ger</mods:languageTerm>
                  </mods:language>
                  <mods:physicalDescription>
                    <mods:internetMediaType>application/pdf</mods:internetMediaType>
                  </mods:physicalDescription>
                  <mods:abstract lang="ger">Von 1989 bis 1992 wurde die EGIG-Linie (Expedition Glaciologique Internationale au Groenland) quer über das grönländische Inlandeis rekonstruiert und nachgemessen. Mit dem elektromagnetischen Reflexionsverfahren (EMR, Eisradar) wurden 49 der 54 Punkte aufgefunden. Dazu wurden Modellrechnungen mit Finiten Differenzen durchgeführt.&#13;
Messungen von Mächtigkeit und innerem Aufbau des Eises wurden an Leitfähigkeits- und Altersdaten der Eiskernbohrungen GRIP und GISP2 kalibriert und lieferten die präzise Felstopographie. Mit CMP-Messungen (CDP) und Laufzeit-Tiefen-Transformationen wurden Reflexionshorizonte sauren Ablagerungen vulkanischer Ereignissen zugeordnet. Sie korrelieren mit der Leitfähigkeit (ECM) des GRIP-Eiskerns. Aus den Reflexionen wurden mittlere jährliche Schichtdicken bestimmt, die mit 2D-Modellrechnung in mittlere jährliche Akkumulationen überführt wurden. Aus Strukturen im Firnbereich ließ sich die Tiefenabhängigkeit der Fließgeschwindigkeit bestimmen.</mods:abstract>
                  <mods:note type="citation/reference">Zugl.: Münster (Westfalen), Univ., Diss., 1994</mods:note>
                  <mods:subject>
                    <mods:topic lang="ger">Glaziologie; Grönland; Summit; GRIP; EGIG; Eis; Radar; Reflektion; Felsgrund; Eiskern; GISP; Isochronen</mods:topic>
                  </mods:subject>
                  <mods:classification authority="ddc">550</mods:classification>
                  <mods:identifier type="urn">urn:nbn:de:hbz:6-84659642088</mods:identifier>
                  <mods:location>
                    <mods:url access="object in context">https://miami.uni-muenster.de/Record/d031be29-f6f4-45c7-9a04-f68a22fdb467</mods:url>
                  </mods:location>
                  <mods:accessCondition type="use and reproduction">
                    <mods:extension>
                      <ma:maWrap xmlns:ma="http://memoryalpha.ulb.uni-muenster.de">
                        <ma:licence>
                          <ma:displayLabel>InC 1.0</ma:displayLabel>
                          <ma:targetUrl>https://rightsstatements.org/vocab/InC/1.0/</ma:targetUrl>
                        </ma:licence>
                      </ma:maWrap>
                    </mods:extension>
                  </mods:accessCondition>
                  <mods:recordInfo>
                    <mods:recordIdentifier>oai:wwu.de:d031be29-f6f4-45c7-9a04-f68a22fdb467</mods:recordIdentifier>
                  </mods:recordInfo>
                </mods:mods>
              </mets:xmlData>
            </mets:mdWrap>
          </mets:dmdSec>
          <mets:amdSec ID="AMD_d031be29-f6f4-45c7-9a04-f68a22fdb467">
            <mets:rightsMD ID="RIGHTSMD_d031be29-f6f4-45c7-9a04-f68a22fdb467">
              <mets:mdWrap MDTYPE="OTHER" MIMETYPE="text/xml" OTHERMDTYPE="DVRIGHTS">
                <mets:xmlData>
                  <dv:rights xmlns:dv="http://dfg-viewer.de/">
                    <dv:owner>Universitäts- und Landesbibliothek Münster</dv:owner>
                  </dv:rights>
                </mets:xmlData>
              </mets:mdWrap>
            </mets:rightsMD>
            <mets:digiprovMD ID="DIGIPROVMD_d031be29-f6f4-45c7-9a04-f68a22fdb467">
              <mets:mdWrap MDTYPE="OTHER" MIMETYPE="text/xml" OTHERMDTYPE="DVLINKS">
                <mets:xmlData>
                  <dv:links xmlns:dv="http://dfg-viewer.de/">
                    <dv:reference>https://miami.uni-muenster.de/Record/d031be29-f6f4-45c7-9a04-f68a22fdb467</dv:reference>
                    <dv:presentation/>
                  </dv:links>
                </mets:xmlData>
              </mets:mdWrap>
            </mets:digiprovMD>
          </mets:amdSec>
          <mets:fileSec>
            <mets:fileGrp USE="DEFAULT">
              <mets:file MIMETYPE="application/pdf" CHECKSUM="edf7a991296ddc8caee6c365c82ee6851e706239a6a84fd5da017dcbb20d3118" CREATED="2016-06-14T15:14:19" CHECKSUMTYPE="SHA-256" SIZE="4793114" ID="ID_FIL_01_diss_hempel.pdf_DEFAULT">
                <mets:FLocat xlink:href="https://repositorium.uni-muenster.de/document/miami/d031be29-f6f4-45c7-9a04-f68a22fdb467/01_diss_hempel.pdf" LOCTYPE="URL"/>
              </mets:file>
              <mets:file MIMETYPE="application/pdf" CHECKSUM="656dea2397e5705bef7dd2be96be87d75149e34ea82e88f7cf184be5c4a66bcb" CREATED="2016-06-14T15:14:19" CHECKSUMTYPE="SHA-256" SIZE="8445455" ID="ID_FIL_03_diss_hempel.pdf_DEFAULT">
                <mets:FLocat xlink:href="https://repositorium.uni-muenster.de/document/miami/d031be29-f6f4-45c7-9a04-f68a22fdb467/03_diss_hempel.pdf" LOCTYPE="URL"/>
              </mets:file>
              <mets:file MIMETYPE="application/pdf" CHECKSUM="4b264c837a71683a1fd7e3bad81fffd470bac900cf82e49e23348747cd3dd3dc" CREATED="2016-06-14T15:14:19" CHECKSUMTYPE="SHA-256" SIZE="3433908" ID="ID_FIL_04_diss_hempel.pdf_DEFAULT">
                <mets:FLocat xlink:href="https://repositorium.uni-muenster.de/document/miami/d031be29-f6f4-45c7-9a04-f68a22fdb467/04_diss_hempel.pdf" LOCTYPE="URL"/>
              </mets:file>
              <mets:file MIMETYPE="application/pdf" CHECKSUM="dcb5f8354b32bec64efc6c82ab0abad2b7e26835db6553e502d9134f197411e6" CREATED="2016-06-14T15:14:19" CHECKSUMTYPE="SHA-256" SIZE="9138012" ID="ID_FIL_02_diss_hempel.pdf_DEFAULT">
                <mets:FLocat xlink:href="https://repositorium.uni-muenster.de/document/miami/d031be29-f6f4-45c7-9a04-f68a22fdb467/02_diss_hempel.pdf" LOCTYPE="URL"/>
              </mets:file>
            </mets:fileGrp>
            <mets:fileGrp USE="DOWNLOAD">
              <mets:file MIMETYPE="application/zip" ID="DOWd031be29-f6f4-45c7-9a04-f68a22fdb467">
                <mets:FLocat xlink:href="https://repositorium.uni-muenster.de/transfer/miami/d031be29-f6f4-45c7-9a04-f68a22fdb467" LOCTYPE="URL"/>
              </mets:file>
            </mets:fileGrp>
          </mets:fileSec>
          <mets:structMap TYPE="PHYSICAL">
            <mets:div ID="ID_PHY_d031be29-f6f4-45c7-9a04-f68a22fdb467" TYPE="physSequence">
              <mets:div ID="ID_PHY_01_diss_hempel.pdf">
                <mets:fptr FILEID="ID_FIL_01_diss_hempel.pdf_DEFAULT"/>
                <mets:fptr FILEID="ID_FIL_03_diss_hempel.pdf_DEFAULT"/>
                <mets:fptr FILEID="ID_FIL_04_diss_hempel.pdf_DEFAULT"/>
                <mets:fptr FILEID="ID_FIL_02_diss_hempel.pdf_DEFAULT"/>
              </mets:div>
            </mets:div>
          </mets:structMap>
          <mets:structMap TYPE="LOGICAL">
            <mets:div ADMID="AMD_d031be29-f6f4-45c7-9a04-f68a22fdb467" DMDID="DMD_d031be29-f6f4-45c7-9a04-f68a22fdb467" ID="ID_LOG_d031be29-f6f4-45c7-9a04-f68a22fdb467" TYPE="Monograph">
              <mets:div ID="ID_LOG_ID_PHY_01_diss_hempel.pdf"/>
              <mets:div ID="ID_LOG_ID_PHY_03_diss_hempel.pdf"/>
              <mets:div ID="ID_LOG_ID_PHY_04_diss_hempel.pdf"/>
              <mets:div ID="ID_LOG_ID_PHY_02_diss_hempel.pdf"/>
            </mets:div>
          </mets:structMap>
          <mets:structLink>
            <mets:smLink xlink:from="ID_LOG_d031be29-f6f4-45c7-9a04-f68a22fdb467" xlink:to="ID_PHY_d031be29-f6f4-45c7-9a04-f68a22fdb467"/>
            <mets:smLink xlink:from="ID_LOG_ID_PHY_04_diss_hempel.pdf" xlink:to="ID_PHY_04_diss_hempel.pdf"/>
            <mets:smLink xlink:from="ID_LOG_ID_PHY_02_diss_hempel.pdf" xlink:to="ID_PHY_02_diss_hempel.pdf"/>
            <mets:smLink xlink:from="ID_LOG_ID_PHY_03_diss_hempel.pdf" xlink:to="ID_PHY_03_diss_hempel.pdf"/>
            <mets:smLink xlink:from="ID_LOG_ID_PHY_01_diss_hempel.pdf" xlink:to="ID_PHY_01_diss_hempel.pdf"/>
          </mets:structLink>
        </mets:mets>