<mets:mets xmlns:mets="http://www.loc.gov/METS/" xmlns:xlink="http://www.w3.org/1999/xlink" xsi:schemaLocation="http://www.loc.gov/METS/ https://www.loc.gov/standards/mets/mets.xsd" OBJID="oai:wwu.de:fdc93607-cae8-4826-90e6-10b987d80cd3" LABEL="University of Muenster, Institutional Repository MIAMI"  xmlns:xsi="http://www.w3.org/2001/XMLSchema-instance">
          <mets:metsHdr CREATEDATE="2022-11-09T15:03:59">
            <mets:agent TYPE="OTHER" ROLE="OTHER" OTHERTYPE="SOFTWARE">
              <mets:name>Memory Alpha</mets:name>
            </mets:agent>
          </mets:metsHdr>
          <mets:dmdSec ID="DMD_fdc93607-cae8-4826-90e6-10b987d80cd3">
            <mets:mdWrap MIMETYPE="text/xml" MDTYPE="MODS">
              <mets:xmlData>
                <mods:mods xmlns:mods="http://www.loc.gov/mods/v3" xsi:schemaLocation="http://www.loc.gov/mods/v3 http://www.loc.gov/standards/mods/v3/mods-3-7.xsd" version="3.7">
                  <mods:titleInfo type="uniform" lang="ger">
                    <mods:title script="Latn">Urbanisierte Musik</mods:title>
                    <mods:subTitle>eine Studie über gesellschaftliche Determinanten musikalischer Raumproduktion und Raumaneignung</mods:subTitle>
                  </mods:titleInfo>
                  <mods:name type="personal" valueURI="http://d-nb.info/gnd/172691680">
                    <mods:namePart type="given">Eberhard</mods:namePart>
                    <mods:namePart type="family">Hüppe</mods:namePart>
                    <mods:namePart type="date">1955-</mods:namePart>
                    <mods:displayForm>Hüppe, Eberhard</mods:displayForm>
                    <mods:affiliation>FB 15: Musikhochschule</mods:affiliation>
                    <mods:role>
                      <mods:roleTerm type="code" authority="marcrelator">aut</mods:roleTerm>
                    </mods:role>
                  </mods:name>
                  <mods:name type="corporate" valueURI="http://d-nb.info/gnd/5091030-9" altRepGroup="1">
                    <mods:namePart>Universitäts- und Landesbibliothek Münster</mods:namePart>
                    <mods:role>
                      <mods:roleTerm type="code" authority="marcrelator">own</mods:roleTerm>
                    </mods:role>
                  </mods:name>
                  <mods:name type="corporate" valueURI="http://d-nb.info/gnd/5091030-9" altRepGroup="1">
                    <mods:namePart>Münster, Westfalen / ULB</mods:namePart>
                    <mods:role>
                      <mods:roleTerm type="code" authority="marcrelator">own</mods:roleTerm>
                    </mods:role>
                  </mods:name>
                  <mods:name type="corporate" valueURI="http://d-nb.info/gnd/5091030-9" altRepGroup="1">
                    <mods:namePart>Münster, Westfalen / Landesbibliothek</mods:namePart>
                    <mods:role>
                      <mods:roleTerm type="code" authority="marcrelator">own</mods:roleTerm>
                    </mods:role>
                  </mods:name>
                  <mods:name type="corporate" valueURI="http://d-nb.info/gnd/5091030-9" altRepGroup="1">
                    <mods:namePart>Westfalen / Universität Münster / Universitäts- und Landesbibliothek</mods:namePart>
                    <mods:role>
                      <mods:roleTerm type="code" authority="marcrelator">own</mods:roleTerm>
                    </mods:role>
                  </mods:name>
                  <mods:genre>book</mods:genre>
                  <mods:genre authority="dct">Text</mods:genre>
                  <mods:originInfo>
                    <mods:dateIssued keyDate="yes">2012</mods:dateIssued>
                    <mods:edition>gedruckte Ausgabe</mods:edition>
                  </mods:originInfo>
                  <mods:originInfo>
                    <mods:dateIssued encoding="w3cdtf">2012-04-02</mods:dateIssued>
                    <mods:dateModified encoding="w3cdtf">2015-01-09</mods:dateModified>
                    <mods:edition>[Electronic ed.]</mods:edition>
                  </mods:originInfo>
                  <mods:language>
                    <mods:languageTerm type="code" authority="iso639-2b">ger</mods:languageTerm>
                  </mods:language>
                  <mods:physicalDescription>
                    <mods:internetMediaType>application/pdf</mods:internetMediaType>
                  </mods:physicalDescription>
                  <mods:abstract lang="ger">Städte sind akustische Systeme mit einer historisch gewachsenen semantischen Bandbreite. Ihr Klangraum stiftet Identitäten, fasziniert, schreckt ab, wird in Verbindung gebracht mit musikalischen Traditionen und lokalen Musikstilen, verselbständigt sich zu touristischen Klischees. Ein weites kulturgeschichtliches Feld öffnet sich. Musik, Raum, Klang und Geräusch verbinden sich zu bisweilen widersprüchlichen oder heterotopen Szenarien. Wie setzt sich musikschaffendes Handeln mit solchen Szenarien auseinander? Darauf versucht die vorliegende Studie Antworten zu geben, indem sie musikwissenschaftliche Sachverhalte gesellschaftstheoretisch durchdringt. Raum ist ein gesellschaftliches Produkt: Unter der Maßgabe lassen sich zahlreiche Formen der Hervorbringung von Räumen und Atmosphären durch Musik, Klang und Geräusch auf Prozesse des gesellschaftlichen Wandels beziehen. Im 19. Jahrhundert verändert dieser Wandel die urbane Klangwelt durchgreifend. Räumliche Wirklichkeiten werden zum Gegenstand des musikalischen Schaffens – empirisch, ästhetisch und strukturell. &lt;br&gt;</mods:abstract>
                  <mods:tableOfContents lang="ger">Einleitung ….. 9&#13;
Erster Teil: Soziologie und Musikforschung im räumlichen Diskurs&#13;
1. Raum und Klang im kultursoziologischen Prozeß&#13;
1.1 Heterotopie und Unruhe ….. 17&#13;
1.1.1 Einspruch der Kulturwissenschaft ….. 19&#13;
1.1.2 Raum als ideologisches Problem: Entwicklung und Orientierung von Fortschritt ….. 21&#13;
1.2. Raum und Sozialtopologie ….. 32&#13;
1.2.1 Raum als Kategorie mehrdimensionaler Analytik ….. 34&#13;
1.2.2 Übergang zur Sozialtopologie: Der Habitus im Geflecht von Feld, Raum und Ort ….. 37&#13;
1.2.3 Die gesellschaftliche Rekursivität objektiver Raumvorstellungen ….. 42&#13;
1.2.4 Wirtschaftsgeographische Einflüsse auf die Entwicklung des Raumdenkens ….. 45&#13;
1.3 Die Großstadt als Determinante räumlicher Transformationen der Wahrnehmung ….. 47&#13;
1.3.1 Theodor Lessing und der Lärm 52&#13;
1.3.2 Georg Simmel: Urbanisierte Erkenntnis ….. 57&#13;
Exkurs über die Verortbarkeit des Hörens ….. 60&#13;
1.3.3 Die Stadt und die Wirklichkeit akustischer Illusionen ….. 64&#13;
1.3.4 Die Widersprüchlichkeit des städtischen Raums ….. 67&#13;
1.3.5 Hören und Sehen in diluvialer Landschaft: Lärm als Urkatastrophe der Wahrnehmung ….. 69&#13;
1.4 Unterwegs zu einer urbanisierten Musik ….. 74&#13;
1.4.1 Gleichzeitigkeit und Synchronisation als symbolische Konstruktion ästhetischer Macht ….. 82&#13;
1.4.2 Raum-Zeit-Phantasmagorien der Liebe: Ludwig van Beethoven und Franz Schubert ….. 89&#13;
1.4.3 Ambivalente Korrespondenzen: Richard Wagner im Raum-Zeit-Geflecht ….. 94&#13;
1.4.4 Musik und Architektur im Rückblick ko-evolutionärer Transformation während der frühen Neuzeit ….. 101&#13;
1.4.5 Die Raum-Zeit-Transformation als Impuls für ästhetische Paradigmenwechsel ….. 102&#13;
2. Räumliches und musikalisches Handeln: Raumsoziologische Perspektiven für die Musiksoziologie&#13;
2.1 Über Raumproduktion (und was Musiktheorie dazu beitragen kann) ….. 105&#13;
2.1.1 Materialität und Immaterialität ….. 108&#13;
2.1.2 Urbanisierte Musik und der räumliche Diskurs der musikalischen Avantgarde ….. 112&#13;
2.1.3 Antikes Intermezzo. Von zwei Kulturen des Musik-Raum-Diskurses ….. 117&#13;
2.1.4 Verräumlichung und Selbstthematisierung ….. 120&#13;
2.2 Raumsoziologische Perspektiven für die Musiksoziologie ….. 128&#13;
2.2.1 Grundlagen raumkonstituierenden Handelns ….. 130&#13;
2.2.2 Musiksoziologie im Widerstreit von Innen- und Außenwelt (Musikalisches Handeln 1) ….. 135&#13;
2.2.3 Körperlichkeit von Praxis und Werk (Musikalisches Handeln 2) ….. 142&#13;
2.2.4 Komponieren als produktive Rezeption (Musikalisches Handeln 3) ….. 153&#13;
2.3 Gattung, Raum und Kontext als Weg zur Wissenschaft vom Werk ….. 162&#13;
2.3.1 Schnittpunkte musikwissenschaftlicher und kunstsoziologischer Gattungstheorien ….. 163&#13;
2.3.2 Mozarts praktische Wissenschaft als Kontextwissen ….. 170&#13;
2.4 Raum und die Konstitution von ›atmosphärischer Objektivation‹ ….. 176&#13;
Zweiter Teil: Urbanisierte Musik&#13;
3. Musikalische Topographien: Venedig, Wien, Paris, New York&#13;
3.1 Urbanisierte Musik und räumliche Eigenlogik ….. 185&#13;
3.2. Venedig: Mehrchörigkeit als Urphänomen urbanisierter Musik ….. 189&#13;
3.2.1 Giovanni Gabrieli – SONATA XX a 22 ….. 196&#13;
3.2.2 Archäologie einer Klanglandschaft: Luigi Nono und Massimo Cacciari hören Venedig ….. 206&#13;
3.3 Um 1908: Einige Möglichkeiten und Gründe, in Wien Dissonanzen zu beobachten ….. 214&#13;
3.3.1 Dissonantes Wissen ….. 220&#13;
3.3.2 Dissonante Distinktionen ….. 225&#13;
3.3.3 Schönbergs Übergang im Rückblick ….. 227&#13;
3.4 Die räumliche Logik des zwölftönigen Raums ….. 229&#13;
3.4.1 Exkurs über das Teilenkönnen von Entdeckungen ….. 237&#13;
3.4.2 Anregungen aus der Kunsttheorie ….. 239&#13;
3.4.3 Geometrie des Notensystems und die Logik des Visuellen ….. 242&#13;
3.5 Im Konnex stadtmusikalischer Eigenlogik: Gustav Mahlers SIEBENTE SYMPHONIE ….. 251&#13;
3.5.1 Eine stadtmusikalische Spurensuche: Reisen, Erleben, Erinnern ….. 257&#13;
3.5.2 Paris oder Das Konzert im Freien ….. 262&#13;
3.5.3 Lindenau, verfremdete Idylle ….. 269&#13;
3.5.4 ›Rondo-Finale‹ ….. 274&#13;
3.6 Integrative Heterogenität und heterogene Integration: Urbanisierte Musik in den USA ….. 282&#13;
3.6.1 Dvo􀄜ák in New York: Konstruktion feldübergreifender Wahrnehmung ….. 283&#13;
3.6.2 Charles Ives’ Entkoppelung von Europa ….. 292&#13;
3.6.3 Raumdenken und Lokalisierung im Transzendentalismus ….. 296&#13;
3.6.4 Dvo􀄜ák, Ives – Mahler. New York im Konnex europäischer Städte ….. 300&#13;
3.7 John Cage und die Besiedlung des Notenpapiers ….. 302&#13;
3.7.1 Der Pionier – ein nationaler Topos ….. 306&#13;
3.7.2 Kognitives Kartieren im raumsoziologischen Kontext ….. 310&#13;
3.7.3 Grenzerkundung als Metapher lebensstilistischer Transformationen ….. 313&#13;
3.7.4 Bild-, Zeichen- und Strukturtransformation ….. 315&#13;
3.7.5 Zufallspragmatik ….. 321&#13;
3.7.6 Unhintergehbarkeit des Intentionalen durch künstlerische Zufallsoperationen ….. 326&#13;
3.7.7 Pierre Boulez und die Metapher des Stadtplans ….. 328&#13;
3.7.8 Eine überraschende Begegnung: Talcott Parsons und der Zen ….. 329&#13;
3.7.9 Die Sternkartenkompositionen ….. 335&#13;
4. Raumkomposition&#13;
4.1 Prolog: An einem Konzertabend ….. 343&#13;
4.1.1 Die Räume der Raumkomposition auf dem Feld der musikalischen Produktion ….. 350&#13;
4.1.2 Akteure der Raumkomposition in Theorielandschaften ….. 362&#13;
4.2 Raumkomposition zwischen urban(isiert)er Semantik und räumlicher Logistik ….. 367&#13;
4.2.1 Wechselwirkungen räumlicher Semantiken und Ausstattungen an symbolträchtigen Orten ….. 369&#13;
4.2.2 Klangarchitektur mit Doppelprofessionalisierung: Iannis Xenakis ….. 373&#13;
4.2.3 Raumkomposition im Geflecht metropolitaner Wissen-Raum-Koppelungen: Paris ….. 375&#13;
4.3 Luigi Nonos Räume der Selbstverortung ….. 382&#13;
4.3.1 Klangwanderung 1959: Aspekte einer Cinematomorphose des Raumklangs ….. 383&#13;
4.3.2 Klangwanderung 1987: Selbstverortung mit Andrej Tarkowskij ….. 386&#13;
4.3.3 Klangwanderung als Gestus und Symbol 3….. 97&#13;
4.3.4 Tableau der Toponymien ….. 402&#13;
4.4 Karlheinz Stockhausen: Raummusik in der Hyperrealität ….. 406&#13;
4.4.1 Raummusik im Themenpark ….. 408&#13;
4.4.2 Kulturalisierung des Religiösen im Feld der musikalischen Avantgarde ….. 415&#13;
4.4.3 Homogenisierung heterogener Räume ….. 425&#13;
4.5 Orte, Inseln und Netze der Avantgarde ….. 432&#13;
4.5.1 ›Les isles joyeuses‹ ….. 434&#13;
4.5.2 Popularkulturelle Implikationen der Neuen Musik: Der ›Sound‹ und Helmut Lachenmann ….. 440&#13;
4.5.3 Epilog ….. 451&#13;
5. Zusammenfassung&#13;
5.1 Musik als Reflexion gesellschaftlicher Verräumlichung ….. 453&#13;
5.2 Produzieren auf dem musikalischen Feld ….. 460&#13;
Literaturverzeichnis ….. 473</mods:tableOfContents>
                  <mods:note type="content">Auch im Buchhandel erhältlich: Urbanisierte Musik : eine Studie über gesellschaftliche Determinanten musikalischer Raumproduktion und Raumaneignung / Eberhard Hüppe. - Münster : Monsenstein und Vannerdat, 2012.- 495 S. (Wissenschaftliche Schriften der WWU Münster : Reihe XVIII ; Bd. 2), ISBN 978-3-8405-0060-2, Preis: 26,80 EUR</mods:note>
                  <mods:note type="citation/reference">Teilw. zugl.: Münster (Westfalen), Univ., Habil.-Schr., 2007</mods:note>
                  <mods:subject>
                    <mods:topic lang="ger">Musikästhetik; Musiksoziologie; Kultursoziologie; Raumsoziologie; Raumkomposition; Sound; Stadt</mods:topic>
                  </mods:subject>
                  <mods:classification authority="ddc">780</mods:classification>
                  <mods:relatedItem type="series">
                    <mods:titleInfo>
                      <mods:title script="Latn">Wissenschaftliche Schriften der WWU Münster / Reihe XVIII</mods:title>
                    </mods:titleInfo>
                    <mods:part type="volume" order="2">
                      <mods:detail>
                        <mods:number>2</mods:number>
                      </mods:detail>
                    </mods:part>
                    <mods:recordInfo>
                      <mods:recordIdentifier>oai:wwu.de:fad3e3f3-6a0a-48c1-b4d7-506db417951b</mods:recordIdentifier>
                    </mods:recordInfo>
                  </mods:relatedItem>
                  <mods:identifier type="urn">urn:nbn:de:hbz:6-21409555523</mods:identifier>
                  <mods:identifier type="isbn">978-3-8405-0060-2</mods:identifier>
                  <mods:location>
                    <mods:url access="object in context">https://miami.uni-muenster.de/Record/fdc93607-cae8-4826-90e6-10b987d80cd3</mods:url>
                  </mods:location>
                  <mods:accessCondition type="use and reproduction">
                    <mods:extension>
                      <ma:maWrap xmlns:ma="http://memoryalpha.ulb.uni-muenster.de">
                        <ma:licence>
                          <ma:displayLabel>InC 1.0</ma:displayLabel>
                          <ma:targetUrl>https://rightsstatements.org/vocab/InC/1.0/</ma:targetUrl>
                        </ma:licence>
                      </ma:maWrap>
                    </mods:extension>
                  </mods:accessCondition>
                  <mods:recordInfo>
                    <mods:recordIdentifier>oai:wwu.de:fdc93607-cae8-4826-90e6-10b987d80cd3</mods:recordIdentifier>
                  </mods:recordInfo>
                </mods:mods>
              </mets:xmlData>
            </mets:mdWrap>
          </mets:dmdSec>
          <mets:amdSec ID="AMD_fdc93607-cae8-4826-90e6-10b987d80cd3">
            <mets:rightsMD ID="RIGHTSMD_fdc93607-cae8-4826-90e6-10b987d80cd3">
              <mets:mdWrap MDTYPE="OTHER" MIMETYPE="text/xml" OTHERMDTYPE="DVRIGHTS">
                <mets:xmlData>
                  <dv:rights xmlns:dv="http://dfg-viewer.de/">
                    <dv:owner>Universitäts- und Landesbibliothek Münster</dv:owner>
                  </dv:rights>
                </mets:xmlData>
              </mets:mdWrap>
            </mets:rightsMD>
            <mets:digiprovMD ID="DIGIPROVMD_fdc93607-cae8-4826-90e6-10b987d80cd3">
              <mets:mdWrap MDTYPE="OTHER" MIMETYPE="text/xml" OTHERMDTYPE="DVLINKS">
                <mets:xmlData>
                  <dv:links xmlns:dv="http://dfg-viewer.de/">
                    <dv:reference>https://miami.uni-muenster.de/Record/fdc93607-cae8-4826-90e6-10b987d80cd3</dv:reference>
                    <dv:presentation/>
                  </dv:links>
                </mets:xmlData>
              </mets:mdWrap>
            </mets:digiprovMD>
          </mets:amdSec>
          <mets:fileSec>
            <mets:fileGrp USE="DEFAULT">
              <mets:file MIMETYPE="application/pdf" CHECKSUM="8327d0471edcfcba05f2b3cb35fe1eadd597001507b0ad32832783ca0589c180" CREATED="2015-01-09T08:05:07" CHECKSUMTYPE="SHA-256" SIZE="6322737" ID="ID_FIL_habil_hueppe_buchblock.pdf_DEFAULT">
                <mets:FLocat xlink:href="https://repositorium.uni-muenster.de/document/miami/fdc93607-cae8-4826-90e6-10b987d80cd3/habil_hueppe_buchblock.pdf" LOCTYPE="URL"/>
              </mets:file>
            </mets:fileGrp>
            <mets:fileGrp USE="DOWNLOAD">
              <mets:file MIMETYPE="application/pdf" ID="DOWfdc93607-cae8-4826-90e6-10b987d80cd3">
                <mets:FLocat xlink:href="https://repositorium.uni-muenster.de/transfer/miami/fdc93607-cae8-4826-90e6-10b987d80cd3" LOCTYPE="URL"/>
              </mets:file>
            </mets:fileGrp>
          </mets:fileSec>
          <mets:structMap TYPE="PHYSICAL">
            <mets:div ID="ID_PHY_fdc93607-cae8-4826-90e6-10b987d80cd3" TYPE="physSequence">
              <mets:div ID="ID_PHY_habil_hueppe_buchblock.pdf">
                <mets:fptr FILEID="ID_FIL_habil_hueppe_buchblock.pdf_DEFAULT"/>
              </mets:div>
            </mets:div>
          </mets:structMap>
          <mets:structMap TYPE="LOGICAL">
            <mets:div ADMID="AMD_fdc93607-cae8-4826-90e6-10b987d80cd3" DMDID="DMD_fdc93607-cae8-4826-90e6-10b987d80cd3" ID="ID_LOG_fdc93607-cae8-4826-90e6-10b987d80cd3" TYPE="Monograph">
              <mets:div ID="ID_LOG_ID_PHY_habil_hueppe_buchblock.pdf"/>
            </mets:div>
          </mets:structMap>
          <mets:structLink>
            <mets:smLink xlink:from="ID_LOG_fdc93607-cae8-4826-90e6-10b987d80cd3" xlink:to="ID_PHY_fdc93607-cae8-4826-90e6-10b987d80cd3"/>
            <mets:smLink xlink:from="ID_LOG_ID_PHY_habil_hueppe_buchblock.pdf" xlink:to="ID_PHY_habil_hueppe_buchblock.pdf"/>
          </mets:structLink>
        </mets:mets>