<mets:mets xmlns:mets="http://www.loc.gov/METS/" xmlns:mods="http://www.loc.gov/mods/v3" xmlns:xlink="http://www.w3.org/1999/xlink">
    <mets:dmdSec ID="DMD_faf3b05b-9d9f-4080-a555-cef9ff8acf39">
        <mets:mdWrap MIMETYPE="text/xml" MDTYPE="MODS">
            <mets:xmlData>
                <mods xmlns="http://www.loc.gov/mods/v3" version="3.7" xmlns:vl="http://visuallibrary.net/vl">
                    <titleInfo lang="ger">
                        <title>Deutsche Wirtschafts- und Sozialgeschichte</title>
                    </titleInfo>
                    <name type="personal" authority="gnd" authorityURI="http://d-nb.info/gnd/" valueURI="http://d-nb.info/gnd/105401498">
                        <displayForm>Teuteberg, Hans J端rgen</displayForm>
                        <namePart type="given">Hans J端rgen</namePart>
                        <namePart type="family">Teuteberg</namePart>
                        <role>
                            <roleTerm type="code" authority="marcrelator">aut</roleTerm>
                        </role>
                    </name>
                    <name type="personal" authority="gnd" authorityURI="http://d-nb.info/gnd/" valueURI="http://d-nb.info/gnd/105401498">
                        <displayForm>Teuteberg, Hans J.</displayForm>
                        <namePart type="given">Hans J.</namePart>
                        <namePart type="family">Teuteberg</namePart>
                        <role>
                            <roleTerm type="code" authority="marcrelator">aut</roleTerm>
                        </role>
                    </name>
                    <name type="personal" authority="gnd" authorityURI="http://d-nb.info/gnd/" valueURI="http://d-nb.info/gnd/105401498">
                        <displayForm>Teuteberg, Hans-J端rgen</displayForm>
                        <namePart type="given">Hans-J端rgen</namePart>
                        <namePart type="family">Teuteberg</namePart>
                        <role>
                            <roleTerm type="code" authority="marcrelator">aut</roleTerm>
                        </role>
                    </name>
                    <typeOfResource>text</typeOfResource>
                    <genre authority="dini">article</genre>
                    <originInfo>
                        <dateIssued encoding="w3cdtf" keyDate="yes">1968</dateIssued>
                        <dateIssued encoding="w3cdtf">2010-09-28</dateIssued>
                        <dateOther encoding="w3cdtf" keyDate="yes">2010-09-29</dateOther>
                    </originInfo>
                    <language>
                        <languageTerm type="code" authority="iso639-2b">ger</languageTerm>
                    </language>
                    <note type="citation/reference">Neue Politische Literatur 13 (1968), 263-265</note>
                    <classification authority="ddc">300</classification>
                    <identifier type="urn">urn:nbn:de:hbz:6-66459458779</identifier>
                    <identifier type="issn">0028-3320</identifier>
                    <accessCondition type="use and reproduction" xlink:href="https://rightsstatements.org/vocab/InC/1.0/">Urheberrechtsschutz</accessCondition>
                    <recordInfo>
                        <recordIdentifier>muenster_miami_faf3b05b-9d9f-4080-a555-cef9ff8acf39</recordIdentifier>
                    </recordInfo>
                    <extension>
                        <vl:doctype>oaArticle</vl:doctype>
                    </extension>
                </mods>
            </mets:xmlData>
        </mets:mdWrap>
    </mets:dmdSec>
    <mets:fileSec>
        <mets:fileGrp USE="pdf upload">
            <mets:file MIMETYPE="application/pdf" ID="FILE_faf3b05b-9d9f-4080-a555-cef9ff8acf39_1">
                <mets:FLocat xlink:href="https://repositorium.uni-muenster.de/document/miami/faf3b05b-9d9f-4080-a555-cef9ff8acf39/1968_teute_deut.pdf" LOCTYPE="URL"/>
            </mets:file>
        </mets:fileGrp>
    </mets:fileSec>
    <mets:structMap TYPE="LOGICAL">
        <mets:div TYPE="document" ID="muenster_miami_faf3b05b-9d9f-4080-a555-cef9ff8acf39" DMDID="DMD_faf3b05b-9d9f-4080-a555-cef9ff8acf39">
            <mets:fptr FILEID="FILE_faf3b05b-9d9f-4080-a555-cef9ff8acf39_1"/>
        </mets:div>
    </mets:structMap>
</mets:mets>
